task2/rom2.sv

module rom2 #(
    parameter ADDRESS_WIDTH = 8,
              DATA_WIDTH = 8
)(
    input logic                     clk,
    input logic [ADDRESS_WIDTH-1:0] addr,
    input logic [DATA_WIDTH-1:0]    phase,
    output logic [DATA_WIDTH-1:0]   dout
);

logic [DATA_WIDTH-1:0] rom_array [2**ADDRESS_WIDTH-1:0];

initial begin
    $display("Loading rom.");
    $readmemh("sinerom.mem", rom_array);
end;

always_ff @(posedge clk)
    // output is synchronous
    if(addr + phase > 0 && addr + phase < 256) dout <= rom_array [addr+phase];


endmodule

task2/rom.sv

module rom #(
    parameter ADDRESS_WIDTH = 8,
              DATA_WIDTH = 8
)(
    input logic                 clk,
    input logic [ADDRESS_WIDTH-1:0] addr,
    output logic [DATA_WIDTH-1:0] dout
);

logic [DATA_WIDTH-1:0] rom_array [2**ADDRESS_WIDTH-1:0];

initial begin
    $display("Loading rom.");
    $readmemh("sinerom.mem", rom_array);
end;

always_ff @(posedge clk)
    // output is synchronous
    dout <= rom_array [addr];

endmodule

task2/counter.sv
module counter #(
    parameter WIDTH = 8
)(
    //interface signals
    input  logic                clk,   //clock
    input  logic                rst,   //reset
    input  logic                en,    // counter enable
    input  logic    [WIDTH-1:0] incr,

    output  logic [WIDTH-1:0]   count  // count output
);

always_ff @ (posedge clk, posedge rst)
    if (rst) count <= {WIDTH{1'b0}};
    else if(en)     count <= count + incr;

endmodule

task2/sinegen.sv
module sinegen #(
    parameter WIDTH = 8
)(
    input logic                 clk,
    input logic                 rst,
    input logic                 en,
    input logic [WIDTH-1:0]     incr,   
    input logic [WIDTH-1:0]     phase,   
    output logic [WIDTH-1:0]    dout,
    output logic [WIDTH-1:0]    dout2,
);

    logic [WIDTH-1:0]           addr;


counter myCounter (
    .clk (clk),
    .en (en),
    .rst (rst),
    .incr (incr),
    .count (addr)
);

rom myRom (
    .clk (clk),
    .addr (addr),
    .dout (dout)
);
rom2 myRom2 (
    .clk (clk),
    .addr (addr),
    .phase (phase),
    .dout (dout2)
);

endmodule

task2/sinegen.vcd
$version Generated by VerilatedVcd $end
$timescale 1ps $end
 $scope module TOP $end
  $var wire 1 # clk $end
  $var wire 1 $ rst $end
  $var wire 1 % en $end
  $var wire 8 & incr [7:0] $end
  $var wire 8 ' phase [7:0] $end
  $var wire 8 ( dout [7:0] $end
  $var wire 8 ) dout2 [7:0] $end
  $scope module sinegen $end
   $var wire 32 + WIDTH [31:0] $end
   $var wire 1 # clk $end
   $var wire 1 $ rst $end
   $var wire 1 % en $end
   $var wire 8 & incr [7:0] $end
   $var wire 8 ' phase [7:0] $end
   $var wire 8 ( dout [7:0] $end
   $var wire 8 ) dout2 [7:0] $end
   $var wire 8 * addr [7:0] $end
   $scope module myCounter $end
    $var wire 32 + WIDTH [31:0] $end
    $var wire 1 # clk $end
    $var wire 1 $ rst $end
    $var wire 1 % en $end
    $var wire 8 & incr [7:0] $end
    $var wire 8 * count [7:0] $end
   $upscope $end
   $scope module myRom $end
    $var wire 32 + ADDRESS_WIDTH [31:0] $end
    $var wire 32 + DATA_WIDTH [31:0] $end
    $var wire 1 # clk $end
    $var wire 8 * addr [7:0] $end
    $var wire 8 ( dout [7:0] $end
   $upscope $end
   $scope module myRom2 $end
    $var wire 32 + ADDRESS_WIDTH [31:0] $end
    $var wire 32 + DATA_WIDTH [31:0] $end
    $var wire 1 # clk $end
    $var wire 8 * addr [7:0] $end
    $var wire 8 ' phase [7:0] $end
    $var wire 8 ) dout [7:0] $end
   $upscope $end
  $upscope $end
 $upscope $end
$enddefinitions $end


#0
1#
0$
1%
b00001000 &
b00101000 '
b00000000 (
b00000000 )
b00000000 *
b00000000000000000000000000001000 +
#1
0#
#2
1#
b00110011 '
b11111110 (
b11000101 )
b00001000 *
#3
0#
#4
1#
b11111011 (
b10001110 )
b00010000 *
#5
0#
#6
1#
b11110100 (
b01110101 )
b00011000 *
#7
0#
#8
1#
b11101000 (
b01011101 )
b00100000 *
#9
0#
#10
1#
b11011000 (
b01000101 )
b00101000 *
#11
0#
#12
1#
b11000101 (
b00110000 )
b00110000 *
#13
0#
#14
1#
b10101111 (
b00011110 )
b00111000 *
#15
0#
#16
1#
b10010111 (
b00010000 )
b01000000 *
#17
0#
#18
1#
b01111110 (
b00000110 )
b01001000 *
#19
0#
#20
1#
b01100110 (
b00000000 )
b01010000 *
#21
0#
#22
1#
b01001110 (
b01011000 *
#23
0#
#24
1#
b00111000 (
b00000100 )
b01100000 *
#25
0#
#26
1#
b00100101 (
b00001101 )
b01101000 *
#27
0#
#28
1#
b00010101 (
b00011010 )
b01110000 *
#29
0#
#30
1#
b00001001 (
b00101100 )
b01111000 *
#31
0#
#32
1#
b00000010 (
b01000000 )
b10000000 *
#33
0#
#34
1#
b00000000 (
b01010111 )
b10001000 *
#35
0#
#36
1#
b00000010 (
b01101111 )
b10010000 *
#37
0#
#38
1#
b00001001 (
b10001000 )
b10011000 *
#39
0#
#40
1#
b00010101 (
b10100000 )
b10100000 *
#41
0#
#42
1#
b00100101 (
b10111000 )
b10101000 *
#43
0#
#44
1#
b00111000 (
b11001101 )
b10110000 *
#45
0#
#46
1#
b01001110 (
b11011111 )
b10111000 *
#47
0#
#48
1#
b01100110 (
b11101101 )
b11000000 *
#49
0#
#50
1#
b01111111 (
b11110111 )
b11001000 *
#51
0#
#52
1#
b10010111 (
b11111101 )
b11010000 *
#53
0#
#54
1#
b10101111 (
b11011000 *
#55
0#
#56
1#
b11000101 (
b11100000 *
#57
0#
#58
1#
b11011000 (
b11101000 *
#59
0#
#60
1#
b11101000 (
b11110000 *
#61
0#
#62
1#
b11110100 (
b11111000 *
#63
0#
#64
1#
b11111011 (
b00000000 *
#65
0#
#66
1#
b11111110 (
b10100110 )
b00001000 *
#67
0#
#68
1#
b11111011 (
b10001110 )
b00010000 *
#69
0#
#70
1#
b11110100 (
b01110101 )
b00011000 *
#71
0#
#72
1#
b11101000 (
b01011101 )
b00100000 *
#73
0#
#74
1#
b11011000 (
b01000101 )
b00101000 *
#75
0#
#76
1#
b11000101 (
b00110000 )
b00110000 *
#77
0#
#78
1#
b10101111 (
b00011110 )
b00111000 *
#79
0#
#80
1#
b10010111 (
b00010000 )
b01000000 *
#81
0#
#82
1#
b01111110 (
b00000110 )
b01001000 *
#83
0#
#84
1#
b01100110 (
b00000000 )
b01010000 *
#85
0#
#86
1#
b01001110 (
b01011000 *
#87
0#
#88
1#
b00111000 (
b00000100 )
b01100000 *
#89
0#
#90
1#
b00100101 (
b00001101 )
b01101000 *
#91
0#
#92
1#
b00010101 (
b00011010 )
b01110000 *
#93
0#
#94
1#
b00001001 (
b00101100 )
b01111000 *
#95
0#
#96
1#
b00000010 (
b01000000 )
b10000000 *
#97
0#
#98
1#
b00000000 (
b01010111 )
b10001000 *
#99
0#
#100
1#
b00000010 (
b01101111 )
b10010000 *
#101
0#
#102
1#
b00001001 (
b10001000 )
b10011000 *
#103
0#
#104
1#
b00010101 (
b10100000 )
b10100000 *
#105
0#
#106
1#
b00100101 (
b10111000 )
b10101000 *
#107
0#
#108
1#
b00111000 (
b11001101 )
b10110000 *
#109
0#
#110
1#
b01001110 (
b11011111 )
b10111000 *
#111
0#
#112
1#
b01100110 (
b11101101 )
b11000000 *
#113
0#
#114
1#
b01111111 (
b11110111 )
b11001000 *
#115
0#
#116
1#
b10010111 (
b11111101 )
b11010000 *
#117
0#
#118
1#
b10101111 (
b11011000 *
#119
0#
#120
1#
b11000101 (
b11100000 *
#121
0#
#122
1#
b11011000 (
b11101000 *
#123
0#
#124
1#
b11101000 (
b11110000 *
#125
0#
#126
1#
b11110100 (
b11111000 *
#127
0#
#128
1#
b11111011 (
b00000000 *
#129
0#
#130
1#
b11111110 (
b10100110 )
b00001000 *
#131
0#
#132
1#
b11111011 (
b10001110 )
b00010000 *
#133
0#
#134
1#
b11110100 (
b01110101 )
b00011000 *
#135
0#
#136
1#
b11101000 (
b01011101 )
b00100000 *
#137
0#
#138
1#
b11011000 (
b01000101 )
b00101000 *
#139
0#
#140
1#
b11000101 (
b00110000 )
b00110000 *
#141
0#
#142
1#
b10101111 (
b00011110 )
b00111000 *
#143
0#
#144
1#
b10010111 (
b00010000 )
b01000000 *
#145
0#
#146
1#
b01111110 (
b00000110 )
b01001000 *
#147
0#
#148
1#
b01100110 (
b00000000 )
b01010000 *
#149
0#
#150
1#
b01001110 (
b01011000 *
#151
0#
#152
1#
b00111000 (
b00000100 )
b01100000 *
#153
0#
#154
1#
b00100101 (
b00001101 )
b01101000 *
#155
0#
#156
1#
b00010101 (
b00011010 )
b01110000 *
#157
0#
#158
1#
b00001001 (
b00101100 )
b01111000 *
#159
0#
#160
1#
b00000010 (
b01000000 )
b10000000 *
#161
0#
#162
1#
b00000000 (
b01010111 )
b10001000 *
#163
0#
#164
1#
b00000010 (
b01101111 )
b10010000 *
#165
0#
#166
1#
b00001001 (
b10001000 )
b10011000 *
#167
0#
#168
1#
b00010101 (
b10100000 )
b10100000 *
#169
0#
#170
1#
b00100101 (
b10111000 )
b10101000 *
#171
0#
#172
1#
b00111000 (
b11001101 )
b10110000 *
#173
0#
#174
1#
b01001110 (
b11011111 )
b10111000 *
#175
0#
#176
1#
b01100110 (
b11101101 )
b11000000 *
#177
0#
#178
1#
b01111111 (
b11110111 )
b11001000 *
#179
0#
#180
1#
b10010111 (
b11111101 )
b11010000 *
#181
0#
#182
1#
b10101111 (
b11011000 *
#183
0#
#184
1#
b11000101 (
b11100000 *
#185
0#
#186
1#
b11011000 (
b11101000 *
#187
0#
#188
1#
b11101000 (
b11110000 *
#189
0#
#190
1#
b11110100 (
b11111000 *
#191
0#
#192
1#
b11111011 (
b00000000 *
#193
0#
#194
1#
b11111110 (
b10100110 )
b00001000 *
#195
0#
#196
1#
b11111011 (
b10001110 )
b00010000 *
#197
0#
#198
1#
b11110100 (
b01110101 )
b00011000 *
#199
0#
#200
1#
b11101000 (
b01011101 )
b00100000 *
#201
0#
#202
1#
b00110101 '
b11011000 (
b01000101 )
b00101000 *
#203
0#
#204
1#
b00110111 '
b11000101 (
b00101100 )
b00110000 *
#205
0#
#206
1#
b10101111 (
b00010111 )
b00111000 *
#207
0#
#208
1#
b00111000 '
b10010111 (
b00001010 )
b01000000 *
#209
0#
#210
1#
b00111001 '
b01111110 (
b00000010 )
b01001000 *
#211
0#
#212
1#
b01100110 (
b00000000 )
b01010000 *
#213
0#
#214
1#
b01001110 (
b00000011 )
b01011000 *
#215
0#
#216
1#
b00111010 '
b00111000 (
b00001010 )
b01100000 *
#217
0#
#218
1#
b00111011 '
b00100101 (
b00011000 )
b01101000 *
#219
0#
#220
1#
b00111100 '
b00010101 (
b00101100 )
b01110000 *
#221
0#
#222
1#
b00111110 '
b00001001 (
b01000011 )
b01111000 *
#223
0#
#224
1#
b01000001 '
b00000010 (
b01100000 )
b10000000 *
#225
0#
#226
1#
b01000010 '
b00000000 (
b10000010 )
b10001000 *
#227
0#
#228
1#
b00000010 (
b10011101 )
b10010000 *
#229
0#
#230
1#
b00001001 (
b10110101 )
b10011000 *
#231
0#
#232
1#
b00010101 (
b11001010 )
b10100000 *
#233
0#
#234
1#
b00100101 (
b11011101 )
b10101000 *
#235
0#
#236
1#
b00111000 (
b11101011 )
b10110000 *
#237
0#
#238
1#
b01001110 (
b11110110 )
b10111000 *
#239
0#
#240
1#
b01100110 (
b11111100 )
b11000000 *
#241
0#
#242
1#
b01111111 (
b11001000 *
#243
0#
#244
1#
b10010111 (
b11010000 *
#245
0#
#246
1#
b10101111 (
b11011000 *
#247
0#
#248
1#
b11000101 (
b11100000 *
#249
0#
#250
1#
b01000011 '
b11011000 (
b11101000 *
#251
0#
#252
1#
b01000101 '
b11101000 (
b11110000 *
#253
0#
#254
1#
b01001010 '
b11110100 (
b11111000 *
#255
0#
#256
1#
b01001011 '
b11111011 (
b00000000 *
#257
0#
#258
1#
b01001100 '
b11111110 (
b01011101 )
b00001000 *
#259
0#
#260
1#
b11111011 (
b01000011 )
b00010000 *
#261
0#
#262
1#
b11110100 (
b00101110 )
b00011000 *
#263
0#
#264
1#
b11101000 (
b00011100 )
b00100000 *
#265
0#
#266
1#
b11011000 (
b00001110 )
b00101000 *
#267
0#
#268
1#
b11000101 (
b00000101 )
b00110000 *
#269
0#
#270
1#
b10101111 (
b00000000 )
b00111000 *
#271
0#
#272
1#
b10010111 (
b01000000 *
#273
0#
#274
1#
b01111110 (
b00000101 )
b01001000 *
#275
0#
#276
1#
b01100110 (
b00001110 )
b01010000 *
#277
0#
#278
1#
b01001110 (
b00011100 )
b01011000 *
#279
0#
#280
1#
b00111000 (
b00101110 )
b01100000 *
#281
0#
#282
1#
b00100101 (
b01000011 )
b01101000 *
#283
0#
#284
1#
b00010101 (
b01011010 )
b01110000 *
#285
0#
#286
1#
b00001001 (
b01110010 )
b01111000 *
#287
0#
#288
1#
b00000010 (
b10001011 )
b10000000 *
#289
0#
#290
1#
b00000000 (
b10100011 )
b10001000 *
#291
0#
#292
1#
b00000010 (
b10111010 )
b10010000 *
#293
0#
#294
1#
b00001001 (
b11001111 )
b10011000 *
#295
0#
#296
1#
b00010101 (
b11100001 )
b10100000 *
#297
0#
#298
1#
b01001101 '
b00100101 (
b11101111 )
b10101000 *
#299
0#
#300
1#
b01001110 '
b00111000 (
b11111001 )
b10110000 *
#301
0#
#302
1#
b01001110 (
b11111101 )
b10111000 *
#303
0#
#304
1#
b01001111 '
b01100110 (
b11000000 *
#305
0#
#306
1#
b01010001 '
b01111111 (
b11001000 *
#307
0#
#308
1#
b01010011 '
b10010111 (
b11010000 *
#309
0#
#310
1#
b01010101 '
b10101111 (
b11011000 *
#311
0#
#312
1#
b01010111 '
b11000101 (
b11100000 *
#313
0#
#314
1#
b01011001 '
b11011000 (
b11101000 *
#315
0#
#316
1#
b11101000 (
b11110000 *
#317
0#
#318
1#
b11110100 (
b11111000 *
#319
0#
#320
1#
b01011010 '
b11111011 (
b00000000 *
#321
0#
#322
1#
b11111110 (
b00110011 )
b00001000 *
#323
0#
#324
1#
b11111011 (
b00100000 )
b00010000 *
#325
0#
#326
1#
b11110100 (
b00010010 )
b00011000 *
#327
0#
#328
1#
b11101000 (
b00000111 )
b00100000 *
#329
0#
#330
1#
b11011000 (
b00000001 )
b00101000 *
#331
0#
#332
1#
b11000101 (
b00000000 )
b00110000 *
#333
0#
#334
1#
b10101111 (
b00000011 )
b00111000 *
#335
0#
#336
1#
b10010111 (
b00001100 )
b01000000 *
#337
0#
#338
1#
b01111110 (
b00011000 )
b01001000 *
#339
0#
#340
1#
b01100110 (
b00101001 )
b01010000 *
#341
0#
#342
1#
b01001110 (
b00111101 )
b01011000 *
#343
0#
#344
1#
b00111000 (
b01010100 )
b01100000 *
#345
0#
#346
1#
b00100101 (
b01101100 )
b01101000 *
#347
0#
#348
1#
b00010101 (
b10000101 )
b01110000 *
#349
0#
#350
1#
b01011100 '
b00001001 (
b10011101 )
b01111000 *
#351
0#
#352
1#
b01011101 '
b00000010 (
b10111010 )
b10000000 *
#353
0#
#354
1#
b01011110 '
b00000000 (
b11010001 )
b10001000 *
#355
0#
#356
1#
b01100000 '
b00000010 (
b11100101 )
b10010000 *
#357
0#
#358
1#
b01100001 '
b00001001 (
b11110100 )
b10011000 *
#359
0#
#360
1#
b00010101 (
b11111100 )
b10100000 *
#361
0#
#362
1#
b01100010 '
b00100101 (
b10101000 *
#363
0#
#364
1#
b00111000 (
b10110000 *
#365
0#
#366
1#
b01001110 (
b10111000 *
#367
0#
#368
1#
b01100110 (
b11000000 *
#369
0#
#370
1#
b01111111 (
b11001000 *
#371
0#
#372
1#
b10010111 (
b11010000 *
#373
0#
#374
1#
b10101111 (
b11011000 *
#375
0#
#376
1#
b11000101 (
b11100000 *
#377
0#
#378
1#
b11011000 (
b11101000 *
#379
0#
#380
1#
b01100100 '
b11101000 (
b11110000 *
#381
0#
#382
1#
b11110100 (
b11111000 *
#383
0#
#384
1#
b11111011 (
b00000000 *
#385
0#
#386
1#
b11111110 (
b00011100 )
b00001000 *
#387
0#
#388
1#
b11111011 (
b00001110 )
b00010000 *
#389
0#
#390
1#
b11110100 (
b00000101 )
b00011000 *
#391
0#
#392
1#
b11101000 (
b00000000 )
b00100000 *
#393
0#
#394
1#
b11011000 (
b00101000 *
#395
0#
#396
1#
b11000101 (
b00000101 )
b00110000 *
#397
0#
#398
1#
b10101111 (
b00001110 )
b00111000 *
#399
0#
#400
1#
b10010111 (
b00011100 )
b01000000 *
#401
0#
#402
1#
b01111110 (
b00101110 )
b01001000 *
#403
0#
#404
1#
b01100110 (
b01000011 )
b01010000 *
#405
0#
#406
1#
b01001110 (
b01011010 )
b01011000 *
#407
0#
#408
1#
b00111000 (
b01110010 )
b01100000 *
#409
0#
#410
1#
b00100101 (
b10001011 )
b01101000 *
#411
0#
#412
1#
b00010101 (
b10100011 )
b01110000 *
#413
0#
#414
1#
b00001001 (
b10111010 )
b01111000 *
#415
0#
#416
1#
b00000010 (
b11001111 )
b10000000 *
#417
0#
#418
1#
b00000000 (
b11100001 )
b10001000 *
#419
0#
#420
1#
b00000010 (
b11101111 )
b10010000 *
#421
0#
#422
1#
b00001001 (
b11111000 )
b10011000 *
#423
0#
#424
1#
b00010101 (
b11111101 )
b10100000 *
#425
0#
#426
1#
b00100101 (
b10101000 *
#427
0#
#428
1#
b00111000 (
b10110000 *
#429
0#
#430
1#
b01001110 (
b10111000 *
#431
0#
#432
1#
b01100110 (
b11000000 *
#433
0#
#434
1#
b01111111 (
b11001000 *
#435
0#
#436
1#
b10010111 (
b11010000 *
#437
0#
#438
1#
b10101111 (
b11011000 *
#439
0#
#440
1#
b11000101 (
b11100000 *
#441
0#
#442
1#
b11011000 (
b11101000 *
#443
0#
#444
1#
b11101000 (
b11110000 *
#445
0#
#446
1#
b11110100 (
b11111000 *
#447
0#
#448
1#
b11111011 (
b00000000 *
#449
0#
#450
1#
b11111110 (
b00011100 )
b00001000 *
#451
0#
#452
1#
b11111011 (
b00001110 )
b00010000 *
#453
0#
#454
1#
b11110100 (
b00000101 )
b00011000 *
#455
0#
#456
1#
b11101000 (
b00000000 )
b00100000 *
#457
0#
#458
1#
b11011000 (
b00101000 *
#459
0#
#460
1#
b11000101 (
b00000101 )
b00110000 *
#461
0#
#462
1#
b10101111 (
b00001110 )
b00111000 *
#463
0#
#464
1#
b10010111 (
b00011100 )
b01000000 *
#465
0#
#466
1#
b01111110 (
b00101110 )
b01001000 *
#467
0#
#468
1#
b01100110 (
b01000011 )
b01010000 *
#469
0#
#470
1#
b01001110 (
b01011010 )
b01011000 *
#471
0#
#472
1#
b00111000 (
b01110010 )
b01100000 *
#473
0#
#474
1#
b00100101 (
b10001011 )
b01101000 *
#475
0#
#476
1#
b00010101 (
b10100011 )
b01110000 *
#477
0#
#478
1#
b00001001 (
b10111010 )
b01111000 *
#479
0#
#480
1#
b00000010 (
b11001111 )
b10000000 *
#481
0#
#482
1#
b00000000 (
b11100001 )
b10001000 *
#483
0#
#484
1#
b00000010 (
b11101111 )
b10010000 *
#485
0#
#486
1#
b00001001 (
b11111000 )
b10011000 *
#487
0#
#488
1#
b00010101 (
b11111101 )
b10100000 *
#489
0#
#490
1#
b00100101 (
b10101000 *
#491
0#
#492
1#
b00111000 (
b10110000 *
#493
0#
#494
1#
b01001110 (
b10111000 *
#495
0#
#496
1#
b01100110 (
b11000000 *
#497
0#
#498
1#
b01111111 (
b11001000 *
#499
0#
#500
1#
b10010111 (
b11010000 *
#501
0#
#502
1#
b10101111 (
b11011000 *
#503
0#
#504
1#
b11000101 (
b11100000 *
#505
0#
#506
1#
b11011000 (
b11101000 *
#507
0#
#508
1#
b11101000 (
b11110000 *
#509
0#
#510
1#
b11110100 (
b11111000 *
#511
0#
#512
1#
b11111011 (
b00000000 *
#513
0#
#514
1#
b11111110 (
b00011100 )
b00001000 *
#515
0#
#516
1#
b11111011 (
b00001110 )
b00010000 *
#517
0#
#518
1#
b11110100 (
b00000101 )
b00011000 *
#519
0#
#520
1#
b11101000 (
b00000000 )
b00100000 *
#521
0#
#522
1#
b11011000 (
b00101000 *
#523
0#
#524
1#
b11000101 (
b00000101 )
b00110000 *
#525
0#
#526
1#
b10101111 (
b00001110 )
b00111000 *
#527
0#
#528
1#
b10010111 (
b00011100 )
b01000000 *
#529
0#
#530
1#
b01111110 (
b00101110 )
b01001000 *
#531
0#
#532
1#
b01100110 (
b01000011 )
b01010000 *
#533
0#
#534
1#
b01001110 (
b01011010 )
b01011000 *
#535
0#
#536
1#
b00111000 (
b01110010 )
b01100000 *
#537
0#
#538
1#
b00100101 (
b10001011 )
b01101000 *
#539
0#
#540
1#
b00010101 (
b10100011 )
b01110000 *
#541
0#
#542
1#
b00001001 (
b10111010 )
b01111000 *
#543
0#
#544
1#
b00000010 (
b11001111 )
b10000000 *
#545
0#
#546
1#
b00000000 (
b11100001 )
b10001000 *
#547
0#
#548
1#
b00000010 (
b11101111 )
b10010000 *
#549
0#
#550
1#
b00001001 (
b11111000 )
b10011000 *
#551
0#
#552
1#
b00010101 (
b11111101 )
b10100000 *
#553
0#
#554
1#
b00100101 (
b10101000 *
#555
0#
#556
1#
b00111000 (
b10110000 *
#557
0#
#558
1#
b01001110 (
b10111000 *
#559
0#
#560
1#
b01100110 (
b11000000 *
#561
0#
#562
1#
b01111111 (
b11001000 *
#563
0#
#564
1#
b10010111 (
b11010000 *
#565
0#
#566
1#
b10101111 (
b11011000 *
#567
0#
#568
1#
b11000101 (
b11100000 *
#569
0#
#570
1#
b11011000 (
b11101000 *
#571
0#
#572
1#
b11101000 (
b11110000 *
#573
0#
#574
1#
b11110100 (
b11111000 *
#575
0#
#576
1#
b11111011 (
b00000000 *
#577
0#
#578
1#
b11111110 (
b00011100 )
b00001000 *
#579
0#
#580
1#
b11111011 (
b00001110 )
b00010000 *
#581
0#
#582
1#
b11110100 (
b00000101 )
b00011000 *
#583
0#
#584
1#
b11101000 (
b00000000 )
b00100000 *
#585
0#
#586
1#
b11011000 (
b00101000 *
#587
0#
#588
1#
b11000101 (
b00000101 )
b00110000 *
#589
0#
#590
1#
b10101111 (
b00001110 )
b00111000 *
#591
0#
#592
1#
b10010111 (
b00011100 )
b01000000 *
#593
0#
#594
1#
b01111110 (
b00101110 )
b01001000 *
#595
0#
#596
1#
b01100110 (
b01000011 )
b01010000 *
#597
0#
#598
1#
b01001110 (
b01011010 )
b01011000 *
#599
0#
#600
1#
b00111000 (
b01110010 )
b01100000 *
#601
0#
#602
1#
b00100101 (
b10001011 )
b01101000 *
#603
0#
#604
1#
b00010101 (
b10100011 )
b01110000 *
#605
0#
#606
1#
b00001001 (
b10111010 )
b01111000 *
#607
0#
#608
1#
b00000010 (
b11001111 )
b10000000 *
#609
0#
#610
1#
b00000000 (
b11100001 )
b10001000 *
#611
0#
#612
1#
b00000010 (
b11101111 )
b10010000 *
#613
0#
#614
1#
b00001001 (
b11111000 )
b10011000 *
#615
0#
#616
1#
b00010101 (
b11111101 )
b10100000 *
#617
0#
#618
1#
b00100101 (
b10101000 *
#619
0#
#620
1#
b00111000 (
b10110000 *
#621
0#
#622
1#
b01100011 '
b01001110 (
b10111000 *
#623
0#
#624
1#
b01100110 (
b11000000 *
#625
0#
#626
1#
b01111111 (
b11001000 *
#627
0#
#628
1#
b10010111 (
b11010000 *
#629
0#
#630
1#
b01100010 '
b10101111 (
b11011000 *
#631
0#
#632
1#
b01100001 '
b11000101 (
b11100000 *
#633
0#
#634
1#
b01011111 '
b11011000 (
b11101000 *
#635
0#
#636
1#
b11101000 (
b11110000 *
#637
0#
#638
1#
b11110100 (
b11111000 *
#639
0#
#640
1#
b11111011 (
b00000000 *
#641
0#
#642
1#
b01011110 '
b11111110 (
b00100111 )
b00001000 *
#643
0#
#644
1#
b11111011 (
b00011000 )
b00010000 *
#645
0#
#646
1#
b11110100 (
b00001100 )
b00011000 *
#647
0#
#648
1#
b11101000 (
b00000011 )
b00100000 *
#649
0#
#650
1#
b11011000 (
b00000000 )
b00101000 *
#651
0#
#652
1#
b11000101 (
b00000001 )
b00110000 *
#653
0#
#654
1#
b10101111 (
b00000111 )
b00111000 *
#655
0#
#656
1#
b10010111 (
b00010010 )
b01000000 *
#657
0#
#658
1#
b01111110 (
b00100000 )
b01001000 *
#659
0#
#660
1#
b01100110 (
b00110011 )
b01010000 *
#661
0#
#662
1#
b01001110 (
b01001000 )
b01011000 *
#663
0#
#664
1#
b00111000 (
b01100000 )
b01100000 *
#665
0#
#666
1#
b00100101 (
b01111000 )
b01101000 *
#667
0#
#668
1#
b00010101 (
b10010001 )
b01110000 *
#669
0#
#670
1#
b00001001 (
b10101001 )
b01111000 *
#671
0#
#672
1#
b00000010 (
b11000000 )
b10000000 *
#673
0#
#674
1#
b00000000 (
b11010100 )
b10001000 *
#675
0#
#676
1#
b00000010 (
b11100101 )
b10010000 *
#677
0#
#678
1#
b01011100 '
b00001001 (
b11110001 )
b10011000 *
#679
0#
#680
1#
b01011010 '
b00010101 (
b11111000 )
b10100000 *
#681
0#
#682
1#
b01011000 '
b00100101 (
b11111100 )
b10101000 *
#683
0#
#684
1#
b01010101 '
b00111000 (
b10110000 *
#685
0#
#686
1#
b01010100 '
b01001110 (
b10111000 *
#687
0#
#688
1#
b01010011 '
b01100110 (
b11000000 *
#689
0#
#690
1#
b01111111 (
b11001000 *
#691
0#
#692
1#
b10010111 (
b11010000 *
#693
0#
#694
1#
b10101111 (
b11011000 *
#695
0#
#696
1#
b11000101 (
b11100000 *
#697
0#
#698
1#
b11011000 (
b11101000 *
#699
0#
#700
1#
b11101000 (
b11110000 *
#701
0#
#702
1#
b11110100 (
b11111000 *
#703
0#
#704
1#
b11111011 (
b00000000 *
#705
0#
#706
1#
b11111110 (
b01000101 )
b00001000 *
#707
0#
#708
1#
b11111011 (
b00110000 )
b00010000 *
#709
0#
#710
1#
b11110100 (
b00011110 )
b00011000 *
#711
0#
#712
1#
b11101000 (
b00010000 )
b00100000 *
#713
0#
#714
1#
b11011000 (
b00000110 )
b00101000 *
#715
0#
#716
1#
b11000101 (
b00000000 )
b00110000 *
#717
0#
#718
1#
b10101111 (
b00111000 *
#719
0#
#720
1#
b10010111 (
b00000100 )
b01000000 *
#721
0#
#722
1#
b01111110 (
b00001101 )
b01001000 *
#723
0#
#724
1#
b01100110 (
b00011010 )
b01010000 *
#725
0#
#726
1#
b01001110 (
b00101100 )
b01011000 *
#727
0#
#728
1#
b00111000 (
b01000000 )
b01100000 *
#729
0#
#730
1#
b00100101 (
b01010111 )
b01101000 *
#731
0#
#732
1#
b00010101 (
b01101111 )
b01110000 *
#733
0#
#734
1#
b00001001 (
b10001000 )
b01111000 *
#735
0#
#736
1#
b00000010 (
b10100000 )
b10000000 *
#737
0#
#738
1#
b00000000 (
b10111000 )
b10001000 *
#739
0#
#740
1#
b00000010 (
b11001101 )
b10010000 *
#741
0#
#742
1#
b00001001 (
b11011111 )
b10011000 *
#743
0#
#744
1#
b00010101 (
b11101101 )
b10100000 *
#745
0#
#746
1#
b00100101 (
b11110111 )
b10101000 *
#747
0#
#748
1#
b00111000 (
b11111101 )
b10110000 *
#749
0#
#750
1#
b01001110 (
b10111000 *
#751
0#
#752
1#
b01100110 (
b11000000 *
#753
0#
#754
1#
b01111111 (
b11001000 *
#755
0#
#756
1#
b10010111 (
b11010000 *
#757
0#
#758
1#
b10101111 (
b11011000 *
#759
0#
#760
1#
b11000101 (
b11100000 *
#761
0#
#762
1#
b11011000 (
b11101000 *
#763
0#
#764
1#
b11101000 (
b11110000 *
#765
0#
#766
1#
b11110100 (
b11111000 *
#767
0#
#768
1#
b11111011 (
b00000000 *
#769
0#
#770
1#
b11111110 (
b01000101 )
b00001000 *
#771
0#
#772
1#
b11111011 (
b00110000 )
b00010000 *
#773
0#
#774
1#
b11110100 (
b00011110 )
b00011000 *
#775
0#
#776
1#
b11101000 (
b00010000 )
b00100000 *
#777
0#
#778
1#
b11011000 (
b00000110 )
b00101000 *
#779
0#
#780
1#
b11000101 (
b00000000 )
b00110000 *
#781
0#
#782
1#
b10101111 (
b00111000 *
#783
0#
#784
1#
b10010111 (
b00000100 )
b01000000 *
#785
0#
#786
1#
b01111110 (
b00001101 )
b01001000 *
#787
0#
#788
1#
b01100110 (
b00011010 )
b01010000 *
#789
0#
#790
1#
b01001110 (
b00101100 )
b01011000 *
#791
0#
#792
1#
b00111000 (
b01000000 )
b01100000 *
#793
0#
#794
1#
b00100101 (
b01010111 )
b01101000 *
#795
0#
#796
1#
b00010101 (
b01101111 )
b01110000 *
#797
0#
#798
1#
b00001001 (
b10001000 )
b01111000 *
#799
0#
#800
1#
b00000010 (
b10100000 )
b10000000 *
#801
0#
#802
1#
b00000000 (
b10111000 )
b10001000 *
#803
0#
#804
1#
b00000010 (
b11001101 )
b10010000 *
#805
0#
#806
1#
b00001001 (
b11011111 )
b10011000 *
#807
0#
#808
1#
b00010101 (
b11101101 )
b10100000 *
#809
0#
#810
1#
b00100101 (
b11110111 )
b10101000 *
#811
0#
#812
1#
b00111000 (
b11111101 )
b10110000 *
#813
0#
#814
1#
b01001110 (
b10111000 *
#815
0#
#816
1#
b01100110 (
b11000000 *
#817
0#
#818
1#
b01111111 (
b11001000 *
#819
0#
#820
1#
b10010111 (
b11010000 *
#821
0#
#822
1#
b10101111 (
b11011000 *
#823
0#
#824
1#
b11000101 (
b11100000 *
#825
0#
#826
1#
b11011000 (
b11101000 *
#827
0#
#828
1#
b11101000 (
b11110000 *
#829
0#
#830
1#
b11110100 (
b11111000 *
#831
0#
#832
1#
b11111011 (
b00000000 *
#833
0#
#834
1#
b11111110 (
b01000101 )
b00001000 *
#835
0#
